image_extract/__init__.py
image_extract/ext.py
extract_img_txt-1.0.1.dist-info/LICENSE.txt 
extract_img_txt-1.0.1.dist-info/METADATA
extract_img_txt-1.0.1.dist-info/WHEEL
extract_img_txt-1.0.1.dist-info/top_level.txt
extract_img_txt-1.0.1.dist-info/RECORD
