Metadata-Version: 2.1
Name: extract-img-txt
Version: 1.0.1
Summary: A simple text extractor from image
Author: Iyanuoluwa Akinwumi
Author-email: akinwumikaliyanu@gmail.com
License: :: MIT License
License-File: LICENSE.txt 
Requires-Dist: pytesseract
Requires-Dist: python-docx
Requires-Dist: pillow
